{
    "title": "Movies & Series",
    "series": "Series",
    "movies": "Movies",
    "seeAll": "See all",
    "seeMore": "See more movies",
    "unavailable": "Unavailable",
    "loadingTryAgain": "Try Again",
    "addedOn": "Added on ",
    "season": "Season",
    "seasons": "Seasons",
    "trailer": "Trailer",
    "director": "Director",
    "directors": "Directors",
    "actor": "Actor",
    "actors": "Actors",
    "wishlistEmptyTitle": "No wishes found",
    "wishlistEmptyText": "Add a movie or a serie to your wishlist to see it here!",
    "loadingError": "An error occoured while loading",
    "all": "All",
    "notfound": "Not found",
    "notfound_msg": "The program was not found",
    "action": "Action",
    "comedy": "Comedy",
    "thriller": "Thriller",
    "war": "War",
    "romance": "Romance",
    "drama": "Drama",
    "crime": "Crime",
    "documentary": "Documentary",
    "horror": "Horror"
}